{"is_source_file": false, "format": "JSON", "description": "This is a manifest configuration file (manifest.json) that defines metadata for a web application, including app name, icons, display settings, and theme/background colors.", "external_files": [], "external_methods": [], "published": [], "classes": [], "methods": [], "calls": [], "search-terms": ["manifest", "web app metadata", "icons", "start_url", "display mode", "theme_color"], "state": 2, "file_id": 10, "knowledge_revision": 21, "git_revision": "28daf732e6582380af1f44633f014eeba30d8122", "hash": "d9d975cebe2ec20b6c652e1e4c12ccf0", "format-version": 4, "code-base-name": "notes_app_frontend", "filename": "notes_app_frontend/public/manifest.json", "revision_history": [{"21": "28daf732e6582380af1f44633f014eeba30d8122"}]}